rqlalchemy/__init__.py
rqlalchemy/query.py
rqlalchemy-0.6.0.dist-info/LICENSE
rqlalchemy-0.6.0.dist-info/WHEEL
rqlalchemy-0.6.0.dist-info/METADATA
rqlalchemy-0.6.0.dist-info/RECORD
