Metadata-Version: 2.1
Name: rqlalchemy
Version: 0.6.0
Summary: "Resource Query Language for SQLAlchemy"
Home-page: https://github.com/pjwerneck/rqlalchemy
License: MIT
Keywords: sqlachemy,sql,rql,querying,httpapi
Author: Pedro Werneck
Author-email: pjwerneck@gmail.com
Requires-Python: >=3.8,<4.0
Classifier: License :: OSI Approved :: MIT License
Classifier: Programming Language :: Python :: 3
Classifier: Programming Language :: Python :: 3.8
Classifier: Programming Language :: Python :: 3.9
Classifier: Programming Language :: Python :: 3.10
Classifier: Programming Language :: Python :: 3.11
Requires-Dist: pyrql (>=0.7.8,<0.8.0)
Requires-Dist: sqlalchemy (>=2.0,<3.0)
Project-URL: Repository, https://github.com/pjwerneck/rqlalchemy
